detimer/__init__.py
detimer/__main__.py
detimer/app.py
detimer/commands.py
detimer/config.py
detimer/constants.py
detimer/matcher.py
detimer/rdiff_backup.py
detimer/root.py
detimer/data/default-config.yml
detimer-0.2.1.dist-info/LICENSE
detimer-0.2.1.dist-info/METADATA
detimer-0.2.1.dist-info/WHEEL
detimer-0.2.1.dist-info/entry_points.txt
detimer-0.2.1.dist-info/top_level.txt
detimer-0.2.1.dist-info/RECORD
