Metadata-Version: 2.1
Name: detimer
Version: 0.2.1
Summary: Universal backup manager
Home-page: https://github.com/clabe45/detimer
License-File: LICENSE
Requires-Dist: pyyaml
Requires-Dist: click
